django_profiler/__init__.py
django_profiler/profile.py
sp_django_profiler-1.0.0.dist-info/LICENSE
sp_django_profiler-1.0.0.dist-info/METADATA
sp_django_profiler-1.0.0.dist-info/WHEEL
sp_django_profiler-1.0.0.dist-info/top_level.txt
sp_django_profiler-1.0.0.dist-info/zip-safe
sp_django_profiler-1.0.0.dist-info/RECORD
